{
	"id": "06a558ea-8dcb-47c4-98d8-8842bd5f84e8",
	"name": "GA-SIT1",
	"values": [
		{
			"key": "webendpoint",
			"value": "https://gassitplaydigital1.dev.igt.com",
			"enabled": true
		},
		{
			"key": "mobileendpoint",
			"value": "https://gassitplaydigital1-mobile.dev.igt.com",
			"enabled": true
		},
		{
			"key": "oAuthToken",
			"value": "sbBa3KT78ZJO-WV0iTpOmQ",
			"enabled": true
		},
		{
			"key": "username1",
			"value": "xntjvowqpz@mailinator.com",
			"enabled": true
		},
		{
			"key": "Password1",
			"value": "Password1",
			"enabled": true
		},
		{
			"key": "refreshToken",
			"value": "WAJrm2-2ezxd1Fz1qZyOlQ",
			"enabled": true
		},
		{
			"key": "authCode",
			"value": "nuoNPKUB5tv_na8CisGVMg",
			"enabled": true
		},
		{
			"key": "onePayToken",
			"value": "vF6Low8v4bwIQ8f7w1A0MVjf2jM=",
			"enabled": true
		},
		{
			"key": "T&C Version",
			"value": "29",
			"enabled": true
		},
		{
			"key": "cashierendpoint",
			"value": "https://gassitplaydigital1-cashier.dev.igt.com",
			"enabled": true
		}
	],
	"_postman_variable_scope": "environment",
	"_postman_exported_at": "2020-10-09T14:03:13.236Z",
	"_postman_exported_using": "Postman/7.34.0"
}